leafage/__init__.py
leafage/module.py
leafage/__pycache__/__init__.cpython-37.pyc
leafage/__pycache__/leafage.cpython-37.pyc
leafage/__pycache__/module.cpython-37.pyc
leafage/templates/paginator.html
leafage/templatetags/__init__.py
leafage/templatetags/leafage.py
leafage/templatetags/__pycache__/__init__.cpython-37.pyc
leafage/templatetags/__pycache__/get_varient_image.cpython-37.pyc
django_leafage-1.2.5.dist-info/LICENSE
django_leafage-1.2.5.dist-info/METADATA
django_leafage-1.2.5.dist-info/WHEEL
django_leafage-1.2.5.dist-info/top_level.txt
django_leafage-1.2.5.dist-info/RECORD
