Metadata-Version: 2.1
Name: django-leafage
Version: 1.2.5
Summary: Simple and Easiest paginator for Django.
Home-page: https://github.com/nilesh-kr-dubey/django-leafage
Author: Nilesh Kumar Dubey
Author-email: nileshdubeyindia@gmail.com
License: MIT
Platform: UNKNOWN
Classifier: Environment :: Web Environment
Classifier: Framework :: Django
Classifier: Intended Audience :: Developers
Classifier: License :: OSI Approved :: MIT License
Classifier: Programming Language :: Python :: 3.6
Classifier: Programming Language :: Python :: 3.7
Classifier: Programming Language :: Python :: 3.8
Classifier: Topic :: Internet :: WWW/HTTP
Classifier: Topic :: Internet :: WWW/HTTP :: Dynamic Content
Requires-Dist: Django (>=2.0)
